pysatdata/__init__.py
pysatdata/version.py
pysatdata/utils/__init__.py
pysatdata/utils/cdf_to_tplot.py
pysatdata/utils/dailynames.py
pysatdata/utils/download.py
pysatdata/utils/interpolate_flux_rbsp.py
pysatdata/utils/library_functions.py
pysatdata/utils/netcdf2tplot.py
pysatdata/utils/time_double.py
pysatdata/utils/time_string.py
pysatdata/utils/cotrans/__init__.py
pysatdata/utils/cotrans/cotrans.py
pysatdata/utils/cotrans/cotrans_get_coord.py
pysatdata/utils/cotrans/cotrans_lib.py
pysatdata/utils/cotrans/cotrans_set_coord.py
pysatdata/utils/cotrans/fac_matrix_make.py
pysatdata/utils/cotrans/gsm2lmn.py
pysatdata/utils/cotrans/igrf.py
pysatdata/utils/cotrans/j2000.py
pysatdata/utils/cotrans/matrix_array_lib.py
pysatdata/utils/cotrans/minvar.py
pysatdata/utils/cotrans/minvar_matrix_make.py
pysatdata/utils/cotrans/quaternions.py
pysatdata/utils/cotrans/tvector_rotate.py
pysatdata/utils/cotrans/xyz_to_polar.py
pysatdata/utils/cotrans/tests/__init__.py
pysatdata/utils/cotrans/tests/cotrans.py
pysatdata/utils/cotrans/tests/quaternions.py
pysatdata-2.0.20.dist-info/LICENSE
pysatdata-2.0.20.dist-info/METADATA
pysatdata-2.0.20.dist-info/WHEEL
pysatdata-2.0.20.dist-info/top_level.txt
pysatdata-2.0.20.dist-info/RECORD
