Metadata-Version: 2.1
Name: pysatdata
Version: 2.0.20
Summary: Python Space Physics Satellite Data Analysis Toolkit
Home-page: https://github.com/zemarchezi/pySatData
Author: Jose Paulo Marchezi
Author-email: jose.marchezi@inpe.br, jpmarchezi@gmail.com
License: MIT
Keywords: satellite space data tools
Classifier: Development Status :: 2 - Pre-Alpha
Classifier: Intended Audience :: Science/Research
Classifier: Topic :: Scientific/Engineering
Classifier: License :: OSI Approved :: MIT License
Classifier: Programming Language :: Python :: 3
Requires-Python: >=3.6
License-File: LICENSE
Requires-Dist: requests
Requires-Dist: pyspedas
Requires-Dist: pytplot-mpl-temp >=2.1.17
Requires-Dist: cdflib >=0.3.20
Requires-Dist: cdasws >=1.7.24
Requires-Dist: netCDF4
Requires-Dist: pywavelets
Requires-Dist: astropy
Requires-Dist: pyqtgraph
Requires-Dist: loguru
Requires-Dist: aacgmv2 >=2.6.2
Requires-Dist: matplotlib
Requires-Dist: pandas
Requires-Dist: pytz
Requires-Dist: scipy
Requires-Dist: tqdm
Requires-Dist: xarray
Requires-Dist: urllib3
